qrpic/__init__.py
qrpic/geom/__init__.py
qrpic/itertools/__init__.py
qrpic/main.py
qrpic/svgdom/__init__.py
qrpic/svgdom/transforms.py
qrpic-0.3.dist-info/entry_points.txt
qrpic-0.3.dist-info/LICENSE
qrpic-0.3.dist-info/WHEEL
qrpic-0.3.dist-info/METADATA
qrpic-0.3.dist-info/RECORD
