Metadata-Version: 2.1
Name: qrpic
Version: 0.3
Summary: Create beautiful QR-codes with perfectly fitting logos!
Home-page: https://gitlab.com/Makman2/qrpic
License: MIT
Keywords: qr-code,imaging,logo
Author: Mischa Krueger
Author-email: makmanx64@gmail.com
Requires-Python: >=3.8,<4.0
Classifier: Development Status :: 3 - Alpha
Classifier: Environment :: Console
Classifier: Intended Audience :: End Users/Desktop
Classifier: License :: OSI Approved :: MIT License
Classifier: Natural Language :: English
Classifier: Operating System :: OS Independent
Classifier: Programming Language :: Python :: 3
Classifier: Programming Language :: Python :: 3.8
Classifier: Programming Language :: Python :: 3.9
Classifier: Topic :: Artistic Software
Classifier: Topic :: Printing
Requires-Dist: Shapely (>=1.7.1,<2.0.0)
Requires-Dist: qrcodegen (>=1.6.0,<2.0.0)
Requires-Dist: svg.path (>=4.1,<5.0)
Project-URL: Bug Tracker, https://gitlab.com/Makman2/qrpic/issues
Project-URL: Source Code, https://gitlab.com/Makman2/qrpic/-/tree/master
